{
  "name": {
    "tr": "Ticari Eşya Taşımacılığı",
    "en": "Ticari Eşya shippingcılığı"
  },
  "status": "play",
  "category": "",
  "id": "axypal6s4f",
  "url": "",
  "path": "ticari-esya-tasimaciligi",
  "index": 1,
  "icon": "home",
  "desing": {
    "header": [],
    "body": [],
    "footer": []
  },
  "pathnext": "",
  "spot": {
    "tr": ""
  },
  "desc": {},
  "img": "kj7k5.webp",
  "description": {
    "tr": ""
  },
  "keyword": {
    "tr": ""
  },
  "text": {
    "tr": ""
  },
  "update": "2025-10-06T07:49:43.301Z",
  "date": "2025-10-03T02:30:53.931Z"
}